khoai/__init__.py
khoai/feature_extraction/__init__.py
khoai/feature_extraction/keyex.py
khoai/function/__init__.py
khoai/function/function_.py
khoai/function/metrics.py
khoai/models/__init__.py
khoai/models/base.py
khoai/models/ensemble.py
khoai/models/active_learning/__init__.py
khoai/models/active_learning/base.py
khoai/models/active_learning/entropy_al.py
khoai/models/active_learning/graphdensity_al.py
khoai/models/active_learning/leastconfidence_al.py
khoai/models/active_learning/margin_al.py
khoai/models/active_learning/random_al.py
khoai/models/active_learning/uniform_al.py
khoai/pandas_extension/DataFrame.py
khoai/pandas_extension/__init__.py
khoai/post_processing/__init__.py
khoai/post_processing/tips.py
khoai/pre_processing/__init__.py
khoai/pre_processing/text/__init__.py
khoai/pre_processing/text/n_grams.py
khoai/visualize/__init__.py
khoai/visualize/correlation.py
khoai/visualize/heatmap.py
khoai/visualize/roc_curve.py
khoai-0.1.1.post12.dist-info/LICENSE
khoai-0.1.1.post12.dist-info/METADATA
khoai-0.1.1.post12.dist-info/WHEEL
khoai-0.1.1.post12.dist-info/top_level.txt
khoai-0.1.1.post12.dist-info/RECORD
