Metadata-Version: 2.1
Name: khoai
Version: 0.1.1-12
Summary: A small datascience package
Home-page: https://github.com/lhduc94/khoai
Author: Lê Huỳnh Đức
Author-email: lhduc94@gmail.com
License: UNKNOWN
Platform: UNKNOWN
Classifier: Programming Language :: Python :: 3
Classifier: License :: OSI Approved :: MIT License
Classifier: Operating System :: OS Independent
